matcha_ai/__init__.py
matcha_ai-0.1.0.dist-info/licenses/LICENSE
matcha_ai-0.1.0.dist-info/METADATA
matcha_ai-0.1.0.dist-info/WHEEL
matcha_ai-0.1.0.dist-info/top_level.txt
matcha_ai-0.1.0.dist-info/RECORD
